s5/__init__.py
s5/_version.py
s5/client.py
s5/server.py
s5-0.0.3.dist-info/LICENSE
s5-0.0.3.dist-info/METADATA
s5-0.0.3.dist-info/WHEEL
s5-0.0.3.dist-info/entry_points.txt
s5-0.0.3.dist-info/top_level.txt
s5-0.0.3.dist-info/RECORD
