Metadata-Version: 2.1
Name: s5
Version: 0.0.3
Summary: SciNet Super Simple Secrets Server
Author: Yohai Meiron
Author-email: Yohai Meiron <yohai.meiron@scinet.utoronto.ca>
Classifier: Programming Language :: Python :: 3
Classifier: License :: OSI Approved :: GNU General Public License v3 (GPLv3)
Classifier: Operating System :: OS Independent
Requires-Python: >=3.8
License-File: LICENSE
Requires-Dist: falcon
